piheaan.cpython-38-x86_64-linux-gnu.so
pi_heaan-3.4.1.5.dist-info/METADATA
pi_heaan-3.4.1.5.dist-info/RECORD
pi_heaan-3.4.1.5.dist-info/WHEEL
pi_heaan-3.4.1.5.dist-info/top_level.txt
